setup.cfg
setup.py
ruspython/__init__.py
ruspython.egg-info/PKG-INFO
ruspython.egg-info/SOURCES.txt
ruspython.egg-info/dependency_links.txt
ruspython.egg-info/not-zip-safe
ruspython.egg-info/top_level.txt