Metadata-Version: 2.1
Name: ruspython
Version: 0.0
Summary: перевел функции - методы на русский запустите функцию помоги() чтобы узнать больше (made by Kim)
Home-page: UNKNOWN
Author-email: kimka230510@gmail.com
License: UNKNOWN
Platform: UNKNOWN
